twitterwebhooks/__init__.py
twitterwebhooks/server.py
twitterwebhooks/version.py
twitterwebhooks-1.0.0.dist-info/LICENSE
twitterwebhooks-1.0.0.dist-info/METADATA
twitterwebhooks-1.0.0.dist-info/WHEEL
twitterwebhooks-1.0.0.dist-info/top_level.txt
twitterwebhooks-1.0.0.dist-info/RECORD
